[
  {
    "userId": 616525392
  },
  {
    "userId": 1411561011
  },
  {
    "userId": 857023285
  },
  {
    "userId": 169874053
  },
  {
    "userId": 958536406
  },
  {
    "userId": 550130149
  },
  {
    "userId": 1118602444
  },
  {
    "userId": 1365989453
  },
  {
    "userId": 714403636
  },
  {
    "userId": 1158125023
  },
  {
    "userId": 1542672167
  },
  {
    "userId": 1709102336
  },
  {
    "userId": 1620836523
  },
  {
    "userId": 797322980
  },
  {
    "userId": 1290218390
  },
  {
    "userId": 1310469551
  },
  {
    "userId": 2086842168
  },
  {
    "userId": 710525012
  },
  {
    "userId": 1879127983
  },
  {
    "userId": 1671746260
  },
  {
    "userId": 2013573716
  },
  {
    "userId": 1843783705
  },
  {
    "userId": 1887119342
  },
  {
    "userId": 2124992435
  },
  {
    "userId": 599740414
  }
]